ritual/__init__.py
ritual/__main__.py
ritual/box.py
ritual/editor.py
ritual/lib_pandas.py
ritual/lib_requests.py
ritual/link.py
ritual/slot.py
ritual/static/index.html
ritual/static/css/main.css
ritual/static/js/blueprint.js
ritual/static/js/boxes.js
ritual-0.0.1.dist-info/LICENSE
ritual-0.0.1.dist-info/METADATA
ritual-0.0.1.dist-info/WHEEL
ritual-0.0.1.dist-info/entry_points.txt
ritual-0.0.1.dist-info/top_level.txt
ritual-0.0.1.dist-info/RECORD
