Metadata-Version: 2.1
Name: ritual
Version: 0.0.1
Summary: Visual scripting tool for Python
Home-page: https://github.com/kerighan/ritual
Author: Maixent Chenebaux
Author-email: max.chbx@gmail.com
License: UNKNOWN
Platform: UNKNOWN
Classifier: Programming Language :: Python :: 3
Classifier: Programming Language :: Python :: 3.7
Classifier: License :: OSI Approved :: MIT License
Classifier: Operating System :: OS Independent
Requires-Python: >=3.5
Requires-Dist: flask
Requires-Dist: networkx
Requires-Dist: pandas
Requires-Dist: requests
